tess_publisher-0.9.1.data/scripts/tess_hello
tess_publisher-0.9.1.dist-info/licenses/LICENSE
tesspublisher/__init__.py
tesspublisher/_version.py
tesspublisher/client.py
tesspublisher/constants.py
tesspublisher/http.py
tesspublisher/logger.py
tesspublisher/model.py
tesspublisher/mqtt.py
tesspublisher/photometer.py
tesspublisher/protocol.py
tess_publisher-0.9.1.dist-info/METADATA
tess_publisher-0.9.1.dist-info/WHEEL
tess_publisher-0.9.1.dist-info/entry_points.txt
tess_publisher-0.9.1.dist-info/top_level.txt
tess_publisher-0.9.1.dist-info/RECORD
